dacq2py/OptoCluster.py
dacq2py/__init__.py
dacq2py/axonaIO.py
dacq2py/binning.py
dacq2py/cluster.py
dacq2py/dacq2py_util.py
dacq2py/dacq_comment_finder.py
dacq2py/eegcalcs.py
dacq2py/fieldcalcs.py
dacq2py/gridcell.py
dacq2py/homography.py
dacq2py/lineartrack.py
dacq2py/memoize.py
dacq2py/phaseprecession.py
dacq2py/quicksummary.py
dacq2py/smoothdata.py
dacq2py/spikecalcs.py
dacq2py/statscalcs.py
dacq2py/t_win_SAC.py
dacq2py/tetrode_dict.py
dacq2py/tintcolours.py
dacq2py/utils.py
dacq2py/waveletFunctions.py
dacq2py-0.1.3.dist-info/DESCRIPTION.rst
dacq2py-0.1.3.dist-info/METADATA
dacq2py-0.1.3.dist-info/RECORD
dacq2py-0.1.3.dist-info/WHEEL
dacq2py-0.1.3.dist-info/metadata.json
dacq2py-0.1.3.dist-info/top_level.txt
