Metadata-Version: 2.0
Name: dacq2py
Version: 0.1.3
Summary: Analysis of electrophysiological data recorded with the Axona recording system
Home-page: https://github.com/rhayman/dacq2py
Author: Robin Hayman
Author-email: r.hayman@ucl.ac.uk
License: MIT
Platform: UNKNOWN
Requires-Dist: numpy
Requires-Dist: scipy
Requires-Dist: matplotlib
Requires-Dist: astropy
Requires-Dist: scikit-image
Requires-Dist: mahotas
Requires-Dist: scikits.bootstrap
